[{"id": 13416, "name": "152EVLER MAH."}, {"id": 13447, "name": "75.YIL MAH."}, {"id": 13475, "name": "AK\u00c7A\u011eLAYAN MAH."}, {"id": 13437, "name": "ANADOLU MAH."}, {"id": 13460, "name": "ARABAYATA\u011eI MAH."}, {"id": 13453, "name": "BA\u011eLARALTI MAH."}, {"id": 13443, "name": "BALABAN MAH."}, {"id": 13479, "name": "BARUTHANE MAH."}, {"id": 13431, "name": "BEYAZIT MAH."}, {"id": 49896, "name": "\u00c7ELEB\u0130 MEHMET MAH."}, {"id": 13469, "name": "\u00c7INAR\u00d6N\u00dc MAH."}, {"id": 13476, "name": "CUMALIKIZIK MAH."}, {"id": 13454, "name": "DAVUTDEDE MAH."}, {"id": 13427, "name": "DAVUTKADI MAH."}, {"id": 13466, "name": "DE\u011e\u0130RMENL\u0130KIZIK MAH."}, {"id": 13455, "name": "DE\u011e\u0130RMEN\u00d6N\u00dc MAH."}, {"id": 13471, "name": "DEMETEVLER MAH."}, {"id": 13428, "name": "DUA\u00c7INARI MAH."}, {"id": 13442, "name": "E\u011e\u0130T\u0130M MAH."}, {"id": 13462, "name": "EM\u0130RSULTAN MAH."}, {"id": 13422, "name": "ER\u0130KL\u0130 MAH."}, {"id": 13411, "name": "ERTU\u011eRULGAZ\u0130 MAH."}, {"id": 13434, "name": "ESENEVLER MAH."}, {"id": 13472, "name": "F\u0130DYEKIZIK MAH."}, {"id": 13429, "name": "G\u00dcLL\u00dcK MAH."}, {"id": 13417, "name": "HACISEYFETT\u0130N MAH."}, {"id": 13435, "name": "HAC\u0130VAT MAH."}, {"id": 13473, "name": "HAMAMLIKIZIK MAH."}, {"id": 13412, "name": "HOCATA\u015eKIN MAH."}, {"id": 13440, "name": "\u0130SABEY MAH."}, {"id": 13444, "name": "KAPLIKAYA MAH."}, {"id": 13426, "name": "KARAA\u011eA\u00c7 MAH."}, {"id": 13413, "name": "KARAMAZAK MAH."}, {"id": 13463, "name": "KARAPINAR MAH."}, {"id": 13470, "name": "KAZIM KARABEK\u0130R MAH."}, {"id": 13430, "name": "KURTO\u011eLU MAH."}, {"id": 13418, "name": "MALTEPE MAH."}, {"id": 13414, "name": "MEHMETAK\u0130FERSOY MAH."}, {"id": 13452, "name": "MEVLANA MAH."}, {"id": 13419, "name": "MEYDANCIK MAH."}, {"id": 13457, "name": "M\u0130LLET MAH."}, {"id": 13450, "name": "M\u0130MARS\u0130NAN MAH."}, {"id": 13464, "name": "MOLLAARAP MAH."}, {"id": 13456, "name": "MUSABABA MAH."}, {"id": 13432, "name": "NAMAZGAH MAH."}, {"id": 13436, "name": "ORTABA\u011eLAR MAH."}, {"id": 13445, "name": "P\u0130REM\u0130R MAH."}, {"id": 50306, "name": "SAKARYA MAH."}, {"id": 13465, "name": "SAMANLI MAH."}, {"id": 13420, "name": "SEL\u00c7UKBEY MAH."}, {"id": 13433, "name": "SEL\u0130MZADE MAH."}, {"id": 13467, "name": "S\u0130NANDEDE MAH."}, {"id": 13449, "name": "SIRACEV\u0130ZLER MAH."}, {"id": 13478, "name": "\u015e\u0130R\u0130NEVLER MAH."}, {"id": 13458, "name": "S\u0130TELER MAH."}, {"id": 13441, "name": "\u015e\u00dcKRAN\u0130YE MAH."}, {"id": 13438, "name": "TEFERR\u00dc\u00c7 MAH."}, {"id": 13477, "name": "ULUS MAH."}, {"id": 13423, "name": "UMURBEY MAH."}, {"id": 13415, "name": "VAKIF MAH."}, {"id": 13424, "name": "VATAN MAH."}, {"id": 13446, "name": "YAVUZSELIM MAH."}, {"id": 13451, "name": "YED\u0130SELV\u0130LER MAH."}, {"id": 13448, "name": "YENIMAHALLE MAH."}, {"id": 13468, "name": "YE\u015e\u0130L MAH."}, {"id": 13459, "name": "YE\u015e\u0130LYAYLA MAH."}, {"id": 13439, "name": "Y\u0130\u011e\u0130TLER MAH."}, {"id": 13474, "name": "YILDIRIM MAH."}, {"id": 13425, "name": "YUNUSEMRE MAH."}, {"id": 13461, "name": "ZEYN\u0130LER MAH."}, {"id": 13421, "name": "Z\u00dcMR\u00dcTEVLER MAH."}]