[{"id": 21217, "name": "A\u011eAMEZRASI K\u00d6Y\u00dc"}, {"id": 21190, "name": "AKARBA\u015eI K\u00d6Y\u00dc"}, {"id": 21255, "name": "AKBULAK K\u00d6Y\u00dc"}, {"id": 21250, "name": "AK\u00c7\u0130\u00c7EK K\u00d6Y\u00dc"}, {"id": 50356, "name": "AKKU\u015e K\u00d6Y\u00dc"}, {"id": 50379, "name": "AKPINAR K\u00d6Y\u00dc"}, {"id": 21191, "name": "AKYOKU\u015e K\u00d6Y\u00dc"}, {"id": 21215, "name": "ALABAL K\u00d6Y\u00dc"}, {"id": 49645, "name": "ALAYA\u011eMUR K\u00d6Y\u00dc"}, {"id": 21216, "name": "ALTINOLUK K\u00d6Y\u00dc"}, {"id": 21226, "name": "A\u015eA\u011eIOVACIK K\u00d6Y\u00dc"}, {"id": 21208, "name": "BA\u011eLIA\u011eA\u00c7 K\u00d6Y\u00dc"}, {"id": 21200, "name": "BAH\u00c7EC\u0130K K\u00d6Y\u00dc"}, {"id": 21192, "name": "BAH\u00c7EL\u0130EVLER MAH."}, {"id": 50124, "name": "BALCALI K\u00d6Y\u00dc"}, {"id": 50375, "name": "BARDAKLI K\u00d6Y\u00dc"}, {"id": 21247, "name": "BA\u015eYURT K\u00d6Y\u00dc"}, {"id": 21207, "name": "BAZLAMA K\u00d6Y\u00dc"}, {"id": 50419, "name": "BEYDERE K\u00d6Y\u00dc"}, {"id": 21209, "name": "BULGURCUK K\u00d6Y\u00dc"}, {"id": 21235, "name": "\u00c7ALIKAYA K\u00d6Y\u00dc"}, {"id": 21225, "name": "\u00c7AMARDI K\u00d6Y\u00dc"}, {"id": 21214, "name": "\u00c7ANAK\u00c7I K\u00d6Y\u00dc"}, {"id": 21241, "name": "\u00c7AN K\u00d6Y\u00dc"}, {"id": 21202, "name": "\u00c7ATALYOL K\u00d6Y\u00dc"}, {"id": 21260, "name": "\u00c7AVU\u015eYOLU K\u00d6Y\u00dc"}, {"id": 21213, "name": "\u00c7AYIRDAM K\u00d6Y\u00dc"}, {"id": 21242, "name": "\u00c7AYIRG\u00dcL\u00dc K\u00d6Y\u00dc"}, {"id": 21205, "name": "\u00c7ELEB\u0130 K\u00d6Y\u00dc"}, {"id": 21236, "name": "\u00c7\u0130TAK K\u00d6Y\u00dc"}, {"id": 21243, "name": "CUMHUR\u0130YET K\u00d6Y\u00dc"}, {"id": 21203, "name": "DEM\u0130RDELEN K\u00d6Y\u00dc"}, {"id": 50398, "name": "DEM\u0130RTA\u015e K\u00d6Y\u00dc"}, {"id": 21227, "name": "DEM\u0130RTEPE K\u00d6Y\u00dc"}, {"id": 21204, "name": "DEVEC\u0130 K\u00d6Y\u00dc"}, {"id": 21256, "name": "DO\u011eANO\u011eLU K\u00d6Y\u00dc"}, {"id": 49957, "name": "DUMLUYAZI K\u00d6Y\u00dc"}, {"id": 21210, "name": "DURMU\u015eK\u00d6Y"}, {"id": 21194, "name": "G\u00d6LPINAR MAH."}, {"id": 21251, "name": "G\u00d6ZEREK K\u00d6Y\u00dc"}, {"id": 21232, "name": "G\u00dcLL\u00dcCE K\u00d6Y\u00dc"}, {"id": 50393, "name": "G\u00dcM\u00dc\u015eAKAR K\u00d6Y\u00dc"}, {"id": 21248, "name": "G\u00dcNDE\u011eD\u0130 K\u00d6Y\u00dc"}, {"id": 50383, "name": "HAMURKESEN K\u00d6Y\u00dc"}, {"id": 21228, "name": "HAMZALI K\u00d6Y\u00dc"}, {"id": 21261, "name": "\u0130SABEY K\u00d6Y\u00dc"}, {"id": 21211, "name": "KALEC\u0130K K\u00d6Y\u00dc"}, {"id": 21185, "name": "KALKANKAYA K\u00d6Y\u00dc"}, {"id": 49534, "name": "KARA\u00c7AN K\u00d6Y\u00dc"}, {"id": 21249, "name": "KARAKO\u00c7AN K\u00d6Y\u00dc"}, {"id": 21229, "name": "KARAPINAR K\u00d6Y\u00dc"}, {"id": 49659, "name": "KARASAKAL K\u00d6Y\u00dc"}, {"id": 21244, "name": "KAR\u015eIYAKA MAH."}, {"id": 21252, "name": "KAVAKDERE K\u00d6Y\u00dc"}, {"id": 21186, "name": "KAVALCIK K\u00d6Y\u00dc"}, {"id": 21193, "name": "KEKL\u0130KK\u00d6Y"}, {"id": 21187, "name": "KIRGIL K\u00d6Y\u00dc"}, {"id": 21195, "name": "KIRKPINAR MAH."}, {"id": 21233, "name": "KIZILCA K\u00d6Y\u00dc"}, {"id": 21196, "name": "KIZILPINAR K\u00d6Y\u00dc"}, {"id": 21188, "name": "KOCADAYI K\u00d6Y\u00dc"}, {"id": 21197, "name": "KO\u00c7Y\u0130\u011e\u0130TLER K\u00d6Y\u00dc"}, {"id": 50086, "name": "KORUD\u0130B\u0130 K\u00d6Y\u00dc"}, {"id": 21253, "name": "K\u00d6RYUSUF K\u00d6Y\u00dc"}, {"id": 21230, "name": "KULUBABA MAH."}, {"id": 21198, "name": "KULUNDERE K\u00d6Y\u00dc"}, {"id": 21201, "name": "K\u00dcMBET K\u00d6Y\u00dc"}, {"id": 21212, "name": "KU\u015eBAYIRI K\u00d6Y\u00dc"}, {"id": 21199, "name": "KU\u015e\u00c7U K\u00d6Y\u00dc"}, {"id": 21218, "name": "MAHMUTLU K\u00d6Y\u00dc"}, {"id": 21257, "name": "MAKSUTAL\u0130 K\u00d6Y\u00dc"}, {"id": 21222, "name": "M\u0130RAHMET K\u00d6Y\u00dc"}, {"id": 21189, "name": "OK\u00c7ULAR K\u00d6Y\u00dc"}, {"id": 50397, "name": "ORMANCIK K\u00d6Y\u00dc"}, {"id": 50414, "name": "\u00d6ZL\u00dcCE K\u00d6Y\u00dc"}, {"id": 50425, "name": "PAMUKLU K\u00d6Y\u00dc"}, {"id": 49535, "name": "P\u0130LAVTEPE K\u00d6Y\u00dc"}, {"id": 21237, "name": "SA\u011eIN K\u00d6Y\u00dc"}, {"id": 21219, "name": "SA\u011eUCAK K\u00d6Y\u00dc"}, {"id": 21223, "name": "SARIBA\u015eAK K\u00d6Y\u00dc"}, {"id": 21231, "name": "SARICAN-G\u00d6LYAYLASI MAH."}, {"id": 21234, "name": "SARICAN-SUBA\u015eI MAH."}, {"id": 49579, "name": "SAR\u0130HAN K\u00d6Y\u00dc"}, {"id": 21238, "name": "TEKARDI\u00c7 K\u00d6Y\u00dc"}, {"id": 21245, "name": "TEPE MAH."}, {"id": 21206, "name": "\u00dc\u00c7BUDAK K\u00d6Y\u00dc"}, {"id": 21239, "name": "YALINTA\u015e K\u00d6Y\u00dc"}, {"id": 21221, "name": "YEN\u0130CE K\u00d6Y\u00dc"}, {"id": 49938, "name": "YEN\u0130KAYA K\u00d6Y\u00dc"}, {"id": 21258, "name": "YEN\u0130K\u00d6Y"}, {"id": 21220, "name": "YEN\u0130 MAH."}, {"id": 21259, "name": "YE\u015e\u0130LBELEN K\u00d6Y\u00dc"}, {"id": 21240, "name": "YO\u011eUNA\u011eA\u00c7 K\u00d6Y\u00dc"}, {"id": 21224, "name": "Y\u00dcCEKONAK K\u00d6Y\u00dc"}, {"id": 21246, "name": "YUKARIOVACIK K\u00d6Y\u00dc"}, {"id": 21254, "name": "Y\u00dcZEV K\u00d6Y\u00dc"}]