[{"ballot_box_number": 1022, "cm_result": {"image_url": "https://source3-secim-images.oyveotesi.org/blurred-min/bulk_download/v2/cc63693b-3c56-4f68-9384-ccd6cb172369-1684105086087738853.jpeg", "submission_id": 567332, "total_vote": 226, "votes": {"1": 104, "2": 2, "3": 111, "4": 9}}, "mv_result": {"image_url": "https://secim-images.oyveotesi.org/oyveotesi/blurred-min/server/1881_bulk_999999999_1684094185067105763.jpg", "submission_id": 488949, "total_vote": 228, "votes": {"10": 5, "11": 30, "12": 1, "13": 1, "2": 1, "21": 43, "22": 69, "24": 6, "7": 2, "9": 70}}, "school_name": "HAMZALI K\u00d6Y KONA\u011eI (ESK\u0130 \u0130LKOKUL)"}]