[{"ballot_box_number": 1233, "cm_result": {"image_url": "https://secim-images.oyveotesi.org/oyveotesi/blurred-min/client/8532_cb_1093649425_1684096550463557834.jpeg", "submission_id": 513538, "total_vote": 336, "votes": {"1": 202, "3": 122, "4": 12}}, "mv_result": {"image_url": "https://secim-images.oyveotesi.org/oyveotesi/blurred-min/client/8532_mv_1083649425_1684096710864567889.jpg", "submission_id": 515068, "total_vote": 335, "votes": {"1": 0, "10": 24, "11": 13, "12": 52, "13": 5, "14": 0, "15": 0, "16": 0, "17": 0, "18": 0, "19": 0, "2": 0, "20": 0, "21": 58, "22": 15, "23": 0, "24": 7, "3": 0, "5": 0, "6": 1, "7": 3, "8": 2, "9": 155}}, "school_name": "\u015eEYH\u00dcL\u0130SLAM HAYR\u0130 EFEND\u0130 \u0130LKOKULU"}, {"ballot_box_number": 1234, "cm_result": {"image_url": "https://secim-images.oyveotesi.org/oyveotesi/blurred-min/client/8532_cb_1093649426_1684096728543460406.jpeg", "submission_id": 515248, "total_vote": 321, "votes": {"1": 219, "3": 89, "4": 13}}, "mv_result": null, "school_name": "\u015eEYH\u00dcL\u0130SLAM HAYR\u0130 EFEND\u0130 \u0130LKOKULU"}, {"ballot_box_number": 1235, "cm_result": {"image_url": "https://secim-images.oyveotesi.org/oyveotesi/blurred-min/client/8532_cb_1093649427_1684096805677331316.jpeg", "submission_id": 515978, "total_vote": 337, "votes": {"1": 254, "2": 2, "3": 64, "4": 17}}, "mv_result": {"image_url": "https://secim-images.oyveotesi.org/oyveotesi/blurred-min/client/8532_mv_1083649427_1684096821048266995.jpeg", "submission_id": 516124, "total_vote": 338, "votes": {"10": 29, "11": 25, "12": 28, "13": 3, "14": 1, "15": 0, "16": 0, "17": 0, "18": 0, "19": 0, "2": 0, "20": 0, "21": 22, "22": 9, "23": 0, "24": 8, "3": 0, "4": 0, "5": 7, "6": 0, "7": 3, "8": 7, "9": 196}}, "school_name": "\u015eEYH\u00dcL\u0130SLAM HAYR\u0130 EFEND\u0130 \u0130LKOKULU"}, {"ballot_box_number": 1231, "cm_result": {"image_url": "https://secim-images.oyveotesi.org/oyveotesi/blurred-min/client/8532_cb_1093649423_1684095630197586707.jpeg", "submission_id": 505134, "total_vote": 336, "votes": {"1": 243, "2": 2, "3": 72, "4": 19}}, "mv_result": null, "school_name": "\u015eEYH\u00dcL\u0130SLAM HAYR\u0130 EFEND\u0130 \u0130LKOKULU"}, {"ballot_box_number": 1230, "cm_result": {"image_url": "https://secim-images.oyveotesi.org/oyveotesi/blurred-min/client/8532_cb_1093649422_1684095499060936192.jpeg", "submission_id": 503782, "total_vote": 305, "votes": {"1": 233, "2": 3, "3": 56, "4": 13}}, "mv_result": {"image_url": "https://secim-images.oyveotesi.org/oyveotesi/blurred-min/client/8532_mv_1083649422_1684095511341732871.jpeg", "submission_id": 503911, "total_vote": 295, "votes": {"1": 1, "10": 16, "11": 18, "12": 11, "13": 3, "14": 0, "15": 3, "16": 0, "17": 0, "18": 0, "19": 0, "2": 0, "20": 0, "21": 38, "22": 6, "23": 0, "24": 8, "3": 0, "4": 0, "5": 0, "6": 1, "7": 3, "8": 1, "9": 186}}, "school_name": "\u015eEYH\u00dcL\u0130SLAM HAYR\u0130 EFEND\u0130 \u0130LKOKULU"}, {"ballot_box_number": 1232, "cm_result": {"image_url": "https://secim-images.oyveotesi.org/oyveotesi/blurred-min/client/8532_cb_1093649424_1684096377537287834.jpg", "submission_id": 512098, "total_vote": 315, "votes": {"1": 220, "2": 2, "3": 82, "4": 11}}, "mv_result": {"image_url": "https://secim-images.oyveotesi.org/oyveotesi/blurred-min/client/8532_mv_1083649424_1684096394386468484.jpg", "submission_id": 512223, "total_vote": 316, "votes": {"10": 22, "11": 16, "12": 33, "13": 4, "19": 1, "21": 23, "22": 22, "24": 11, "6": 1, "8": 1, "9": 182}}, "school_name": "\u015eEYH\u00dcL\u0130SLAM HAYR\u0130 EFEND\u0130 \u0130LKOKULU"}]