[{"ballot_box_number": 1020, "cm_result": null, "mv_result": {"image_url": "https://source3-secim-images.oyveotesi.org/blurred-min/bulk_download/v2/b96e6c62-b85d-42f6-afa7-ff745be81819-1684105273048504892.jpg", "submission_id": 609361, "total_vote": 311, "votes": {"1": 1, "10": 34, "11": 52, "13": 1, "21": 11, "22": 15, "24": 4, "7": 2, "8": 5, "9": 186}}, "school_name": "HAD\u0130M\u0130 ANADOLU L\u0130SES\u0130"}, {"ballot_box_number": 1019, "cm_result": {"image_url": "https://source3-secim-images.oyveotesi.org/blurred-min/bulk_download/v2/a7ff9a3a-3dcf-47d9-a33c-4792d7e3c70b-1684105368515111081.jpg", "submission_id": 626881, "total_vote": 313, "votes": {"1": 261, "2": 3, "3": 29, "4": 20}}, "mv_result": null, "school_name": "HAD\u0130M\u0130 ANADOLU L\u0130SES\u0130"}, {"ballot_box_number": 1011, "cm_result": {"image_url": "https://source3-secim-images.oyveotesi.org/blurred-min/bulk_download/v2/5e077a4e-8f67-4862-9123-46d0099d10df-1684105694538057792.jpg", "submission_id": 680953, "total_vote": 337, "votes": {"1": 285, "2": 2, "3": 36, "4": 14}}, "mv_result": {"image_url": "https://source3-secim-images.oyveotesi.org/blurred-min/bulk_download/v2/82de12bb-c1d3-4243-8678-19e60df936b2-1684106022328535288.jpg", "submission_id": 727466, "total_vote": 330, "votes": {"10": 21, "11": 54, "12": 7, "13": 2, "17": 1, "21": 10, "22": 14, "23": 1, "24": 7, "7": 2, "8": 9, "9": 202}}, "school_name": "HAD\u0130M\u0130 ANADOLU L\u0130SES\u0130"}, {"ballot_box_number": 1021, "cm_result": {"image_url": "https://source3-secim-images.oyveotesi.org/blurred-min/bulk_download/v2/0dcebf7a-ffb1-4334-95b4-6126e815f9b8-1684105787619515371.jpg", "submission_id": 695852, "total_vote": 322, "votes": {"1": 273, "2": 1, "3": 33, "4": 15}}, "mv_result": {"image_url": "https://source3-secim-images.oyveotesi.org/blurred-min/bulk_download/v2/dfe198a7-968f-4e63-b498-f165e70cf085-1684105783081174925.jpg", "submission_id": 694915, "total_vote": 313, "votes": {"1": 1, "10": 35, "11": 59, "12": 5, "21": 11, "22": 17, "23": 2, "24": 8, "8": 13, "9": 162}}, "school_name": "HAD\u0130M\u0130 ANADOLU L\u0130SES\u0130"}, {"ballot_box_number": 1002, "cm_result": {"image_url": "https://source3-secim-images.oyveotesi.org/blurred-min/bulk_download/v2/e7fa6fd0-8f10-46cd-9c79-204716c69a77-1684106553513687539.jpg", "submission_id": 804738, "total_vote": 316, "votes": {"1": 273, "3": 35, "4": 8}}, "mv_result": null, "school_name": "HAD\u0130M\u0130 ANADOLU L\u0130SES\u0130"}, {"ballot_box_number": 1005, "cm_result": {"image_url": "https://source3-secim-images.oyveotesi.org/blurred-min/bulk_download/v2/9315c9ec-f046-41c7-bb57-73c882f13997-1684105665194343776.jpg", "submission_id": 676238, "total_vote": 323, "votes": {"1": 296, "3": 22, "4": 5}}, "mv_result": null, "school_name": "HAD\u0130M\u0130 ANADOLU L\u0130SES\u0130"}, {"ballot_box_number": 1008, "cm_result": null, "mv_result": null, "school_name": "HAD\u0130M\u0130 ANADOLU L\u0130SES\u0130"}, {"ballot_box_number": 1004, "cm_result": {"image_url": "https://source3-secim-images.oyveotesi.org/blurred-min/bulk_download/v2/b6395d1c-05df-4fcc-ad0c-64feccaabafd-1684106125588390065.jpg", "submission_id": 742359, "total_vote": 337, "votes": {"1": 275, "2": 1, "3": 41, "4": 20}}, "mv_result": {"image_url": "https://source3-secim-images.oyveotesi.org/blurred-min/bulk_download/v2/4daac26d-7594-46ca-ab24-1b1b0f190839-1684106118328082742.jpg", "submission_id": 742146, "total_vote": 333, "votes": {"10": 36, "11": 54, "12": 1, "19": 1, "21": 22, "22": 14, "23": 1, "24": 10, "7": 2, "8": 8, "9": 184}}, "school_name": "HAD\u0130M\u0130 ANADOLU L\u0130SES\u0130"}, {"ballot_box_number": 1001, "cm_result": {"image_url": "https://source3-secim-images.oyveotesi.org/blurred-min/bulk_download/v2/458573e7-f7ba-4974-aedb-5a92d8329323-1684106748024186300.jpg", "submission_id": 833153, "total_vote": 326, "votes": {"1": 275, "2": 1, "3": 40, "4": 10}}, "mv_result": null, "school_name": "HAD\u0130M\u0130 ANADOLU L\u0130SES\u0130"}, {"ballot_box_number": 1023, "cm_result": {"image_url": "https://source3-secim-images.oyveotesi.org/blurred-min/bulk_download/v2/41a51062-ac69-4d3e-80ac-9e0a883f1f3d-1684106199651527632.jpg", "submission_id": 753744, "total_vote": 323, "votes": {"1": 267, "2": 1, "3": 37, "4": 18}}, "mv_result": null, "school_name": "HAD\u0130M\u0130 ANADOLU L\u0130SES\u0130"}, {"ballot_box_number": 1016, "cm_result": {"image_url": "https://source3-secim-images.oyveotesi.org/blurred-min/bulk_download/v2/ab0c0dc5-d636-41fa-bb27-267e475679a3-1684105808569574198.jpg", "submission_id": 698809, "total_vote": 335, "votes": {"1": 275, "3": 29, "4": 31}}, "mv_result": null, "school_name": "HAD\u0130M\u0130 ANADOLU L\u0130SES\u0130"}, {"ballot_box_number": 1003, "cm_result": {"image_url": "https://source3-secim-images.oyveotesi.org/blurred-min/bulk_download/v2/20eb6ba3-9805-49f2-912e-8fe283641690-1684105881288208973.jpg", "submission_id": 708970, "total_vote": 323, "votes": {"1": 267, "3": 39, "4": 17}}, "mv_result": {"image_url": "https://source3-secim-images.oyveotesi.org/blurred-min/bulk_download/v2/82dfb01b-a807-4a74-b172-bf2ca27159f4-1684106080563263992.jpg", "submission_id": 736052, "total_vote": 318, "votes": {"1": 0, "10": 26, "11": 48, "12": 3, "13": 0, "15": 0, "17": 0, "19": 0, "2": 1, "20": 0, "21": 22, "22": 12, "23": 0, "24": 14, "3": 0, "4": 0, "5": 1, "7": 0, "8": 9, "9": 182}}, "school_name": "HAD\u0130M\u0130 ANADOLU L\u0130SES\u0130"}, {"ballot_box_number": 1009, "cm_result": null, "mv_result": null, "school_name": "HAD\u0130M\u0130 ANADOLU L\u0130SES\u0130"}, {"ballot_box_number": 1013, "cm_result": {"image_url": "https://source3-secim-images.oyveotesi.org/blurred-min/bulk_download/v2/ec92fe84-134d-4857-b82d-a47f84402a85-1684106147426601025.jpg", "submission_id": 745355, "total_vote": 341, "votes": {"1": 292, "3": 34, "4": 15}}, "mv_result": {"image_url": "https://source3-secim-images.oyveotesi.org/blurred-min/bulk_download/v2/4c062499-f1b7-4048-bb9f-78f17353259f-1684106139314445581.jpg", "submission_id": 744258, "total_vote": 329, "votes": {"10": 22, "11": 62, "12": 1, "13": 1, "15": 1, "17": 0, "19": 0, "2": 0, "20": 0, "21": 15, "22": 17, "23": 0, "24": 12, "3": 0, "4": 0, "5": 0, "7": 0, "8": 8, "9": 190}}, "school_name": "HAD\u0130M\u0130 ANADOLU L\u0130SES\u0130"}, {"ballot_box_number": 1014, "cm_result": {"image_url": "https://source3-secim-images.oyveotesi.org/blurred-min/bulk_download/v2/ce4f793c-ed35-4191-94e7-abd8b213b80d-1684105737588082729.jpg", "submission_id": 687917, "total_vote": 312, "votes": {"1": 263, "3": 24, "4": 25}}, "mv_result": null, "school_name": "HAD\u0130M\u0130 ANADOLU L\u0130SES\u0130"}, {"ballot_box_number": 1007, "cm_result": null, "mv_result": null, "school_name": "HAD\u0130M\u0130 ANADOLU L\u0130SES\u0130"}, {"ballot_box_number": 1017, "cm_result": null, "mv_result": {"image_url": "https://source3-secim-images.oyveotesi.org/blurred-min/bulk_download/v2/93164c95-fc97-402a-b28f-097fe98e307a-1684105769285611565.jpg", "submission_id": 692567, "total_vote": 318, "votes": {"10": 25, "11": 63, "12": 2, "21": 15, "22": 16, "23": 1, "24": 11, "7": 2, "8": 6, "9": 177}}, "school_name": "HAD\u0130M\u0130 ANADOLU L\u0130SES\u0130"}, {"ballot_box_number": 1015, "cm_result": {"image_url": "https://source3-secim-images.oyveotesi.org/blurred-min/bulk_download/v2/eb18a383-e830-4837-b5c2-85c4a63c6ba4-1684105720605009864.jpg", "submission_id": 684626, "total_vote": 330, "votes": {"1": 291, "2": 2, "3": 14, "4": 23}}, "mv_result": {"image_url": "https://source3-secim-images.oyveotesi.org/blurred-min/bulk_download/v2/75749722-5d83-443e-856e-498f991cfaed-1684106038301692882.jpg", "submission_id": 729947, "total_vote": 322, "votes": {"1": 1, "10": 20, "11": 68, "12": 1, "21": 9, "22": 5, "23": 2, "24": 12, "3": 1, "7": 2, "8": 9, "9": 192}}, "school_name": "HAD\u0130M\u0130 ANADOLU L\u0130SES\u0130"}, {"ballot_box_number": 1006, "cm_result": null, "mv_result": {"image_url": "https://source3-secim-images.oyveotesi.org/blurred-min/bulk_download/v2/70f8325f-386b-4130-89c6-0d627841c9a2-1684106004606036316.jpg", "submission_id": 725313, "total_vote": 310, "votes": {"1": 0, "10": 31, "11": 55, "12": 4, "13": 1, "15": 1, "17": 0, "19": 0, "2": 0, "20": 0, "21": 14, "22": 18, "23": 0, "24": 9, "3": 1, "4": 0, "5": 0, "7": 3, "8": 2, "9": 171}}, "school_name": "HAD\u0130M\u0130 ANADOLU L\u0130SES\u0130"}, {"ballot_box_number": 1018, "cm_result": null, "mv_result": null, "school_name": "HAD\u0130M\u0130 ANADOLU L\u0130SES\u0130"}, {"ballot_box_number": 1012, "cm_result": {"image_url": "https://source3-secim-images.oyveotesi.org/blurred-min/bulk_download/v2/0972faf1-5552-4ec8-a67b-60dfe33cb9d3-1684105704917791974.jpg", "submission_id": 682457, "total_vote": 320, "votes": {"1": 277, "2": 1, "3": 31, "4": 11}}, "mv_result": {"image_url": "https://source3-secim-images.oyveotesi.org/blurred-min/bulk_download/v2/a1450e03-64c1-49d0-a818-7e5f16b6cca0-1684106028656670498.jpg", "submission_id": 728291, "total_vote": 318, "votes": {"1": 0, "10": 28, "11": 50, "12": 6, "13": 1, "15": 0, "17": 0, "19": 1, "2": 0, "20": 0, "21": 9, "22": 12, "23": 0, "24": 3, "3": 0, "4": 1, "5": 0, "7": 0, "8": 3, "9": 204}}, "school_name": "HAD\u0130M\u0130 ANADOLU L\u0130SES\u0130"}, {"ballot_box_number": 1022, "cm_result": {"image_url": "https://source3-secim-images.oyveotesi.org/blurred-min/bulk_download/v2/8835d2e4-a2dc-4d5a-b291-c4c9c865b50a-1684106185164504789.jpg", "submission_id": 751322, "total_vote": 329, "votes": {"1": 275, "2": 2, "3": 29, "4": 23}}, "mv_result": {"image_url": "https://source3-secim-images.oyveotesi.org/blurred-min/bulk_download/v2/96d8eb79-ab76-4bfd-890f-f91929a981df-1684106181846841284.jpg", "submission_id": 750821, "total_vote": 325, "votes": {"1": 0, "10": 26, "11": 75, "12": 3, "13": 0, "15": 0, "17": 0, "19": 0, "2": 1, "20": 0, "21": 8, "22": 20, "23": 0, "24": 13, "3": 0, "4": 0, "5": 0, "7": 3, "8": 4, "9": 172}}, "school_name": "HAD\u0130M\u0130 ANADOLU L\u0130SES\u0130"}, {"ballot_box_number": 1010, "cm_result": {"image_url": "https://source3-secim-images.oyveotesi.org/blurred-min/bulk_download/v2/b53dc38b-ec94-4896-8a6a-9715357830f3-1684105588646745261.jpg", "submission_id": 663445, "total_vote": 318, "votes": {"1": 276, "3": 32, "4": 10}}, "mv_result": null, "school_name": "HAD\u0130M\u0130 ANADOLU L\u0130SES\u0130"}]