[{"ballot_box_number": 2342, "cm_result": {"image_url": "https://source3-secim-images.oyveotesi.org/blurred-min/bulk_download/v2/be901b7a-2bc0-44c3-bd4b-0c4e34adbdd7-1684105263973474626.jpg", "submission_id": 607350, "total_vote": 236, "votes": {"1": 96, "2": 1, "3": 137, "4": 2}}, "mv_result": null, "school_name": "TARIM \u0130L M\u00dcD\u00dcRL\u00dc\u011e\u00dc"}, {"ballot_box_number": 2343, "cm_result": {"image_url": "https://source3-secim-images.oyveotesi.org/blurred-min/bulk_download/v2/f0208503-592e-4434-ae9c-eaf7e089373b-1684105254172759346.jpg", "submission_id": 605657, "total_vote": 241, "votes": {"1": 111, "3": 123, "4": 7}}, "mv_result": null, "school_name": "TARIM \u0130L M\u00dcD\u00dcRL\u00dc\u011e\u00dc"}, {"ballot_box_number": 2344, "cm_result": null, "mv_result": null, "school_name": "TARIM \u0130L M\u00dcD\u00dcRL\u00dc\u011e\u00dc"}]