[{"ballot_box_number": 1088, "cm_result": {"image_url": "https://secim-images.oyveotesi.org/oyveotesi/blurred-min/client/66377_cb_1093734105_1684093907338545958.jpg", "submission_id": 477281, "total_vote": 332, "votes": {"1": 166, "2": 3, "3": 141, "4": 22}}, "mv_result": {"image_url": "https://secim-images.oyveotesi.org/oyveotesi/blurred-min/client/66377_cb_1093734102_1684093426166439107.jpg", "submission_id": 469714, "total_vote": 331, "votes": {"1": 2, "10": 32, "11": 14, "12": 13, "14": 0, "16": 0, "17": 0, "18": 3, "19": 0, "2": 0, "21": 78, "22": 49, "23": 1, "24": 11, "3": 1, "4": 0, "5": 1, "6": 0, "7": 8, "8": 5, "9": 113}}, "school_name": "TURGUT RE\u0130S \u0130LKOKULU"}, {"ballot_box_number": 1085, "cm_result": {"image_url": "https://secim-images.oyveotesi.org/oyveotesi/blurred-min/client/66377_cb_1093734102_1684093617347927980.jpg", "submission_id": 472031, "total_vote": 326, "votes": {"1": 182, "2": 2, "3": 125, "4": 17}}, "mv_result": {"image_url": "https://secim-images.oyveotesi.org/oyveotesi/blurred-min/client/66377_mv_1083734102_1684093693658001884.jpg", "submission_id": 472935, "total_vote": 328, "votes": {"10": 12, "11": 25, "12": 4, "18": 1, "19": 1, "21": 80, "22": 46, "23": 1, "24": 6, "3": 2, "7": 3, "8": 1, "9": 146}}, "school_name": "TURGUT RE\u0130S \u0130LKOKULU"}, {"ballot_box_number": 1087, "cm_result": {"image_url": "https://secim-images.oyveotesi.org/oyveotesi/blurred-min/client/66377_cb_1093734104_1684093772600446032.jpg", "submission_id": 474018, "total_vote": 348, "votes": {"1": 184, "2": 2, "3": 144, "4": 18}}, "mv_result": {"image_url": "https://source3-secim-images.oyveotesi.org/blurred-min/bulk_download/v2/4faf3035-1a46-4a7c-a13e-321d18cb93bb-1684105772005879286.jpg", "submission_id": 692817, "total_vote": 345, "votes": {"1": 0, "10": 13, "11": 26, "12": 14, "14": 1, "16": 0, "17": 0, "18": 0, "19": 1, "2": 1, "21": 86, "22": 37, "23": 1, "24": 7, "3": 0, "4": 0, "5": 1, "6": 1, "7": 7, "8": 6, "9": 143}}, "school_name": "TURGUT RE\u0130S \u0130LKOKULU"}, {"ballot_box_number": 1086, "cm_result": {"image_url": "https://secim-images.oyveotesi.org/oyveotesi/blurred-min/client/66377_cb_1093734103_1684093714498094992.jpg", "submission_id": 473220, "total_vote": 327, "votes": {"1": 164, "2": 1, "3": 130, "4": 32}}, "mv_result": null, "school_name": "TURGUT RE\u0130S \u0130LKOKULU"}]