[{"ballot_box_number": 1318, "cm_result": {"image_url": "https://secim-images.oyveotesi.org/oyveotesi/blurred-min/server/13138_bulk_999999999_1684093096725332539.jpg", "submission_id": 465295, "total_vote": 344, "votes": {"1": 112, "2": 1, "3": 191, "4": 40}}, "mv_result": {"image_url": "https://secim-images.oyveotesi.org/oyveotesi/blurred-min/server/13138_bulk_999999999_1684093097320955277.jpg", "submission_id": 465307, "total_vote": 342, "votes": {"1": 4, "10": 4, "11": 34, "12": 4, "21": 140, "22": 49, "24": 16, "6": 3, "7": 6, "9": 82}}, "school_name": "FAT\u0130H ANADOLU L\u0130SES\u0130"}, {"ballot_box_number": 1316, "cm_result": {"image_url": "https://secim-images.oyveotesi.org/oyveotesi/blurred-min/server/13138_bulk_999999999_1684093097235702351.jpg", "submission_id": 465305, "total_vote": 342, "votes": {"1": 133, "2": 1, "3": 185, "4": 23}}, "mv_result": null, "school_name": "FAT\u0130H ANADOLU L\u0130SES\u0130"}, {"ballot_box_number": 1315, "cm_result": {"image_url": "https://secim-images.oyveotesi.org/oyveotesi/blurred-min/server/13138_bulk_999999999_1684093096866485387.jpg", "submission_id": 465300, "total_vote": 352, "votes": {"1": 110, "2": 1, "3": 219, "4": 22}}, "mv_result": {"image_url": "https://secim-images.oyveotesi.org/oyveotesi/blurred-min/server/13138_bulk_999999999_1684093293205912399.jpg", "submission_id": 468103, "total_vote": 347, "votes": {"1": 1, "10": 6, "11": 35, "12": 6, "17": 1, "21": 145, "22": 69, "23": 1, "24": 10, "6": 1, "7": 8, "9": 64}}, "school_name": "FAT\u0130H ANADOLU L\u0130SES\u0130"}, {"ballot_box_number": 1317, "cm_result": {"image_url": "https://secim-images.oyveotesi.org/oyveotesi/blurred-min/server/13138_bulk_999999999_1684093293058791255.jpg", "submission_id": 468097, "total_vote": 346, "votes": {"1": 145, "2": 2, "3": 164, "4": 35}}, "mv_result": null, "school_name": "FAT\u0130H ANADOLU L\u0130SES\u0130"}, {"ballot_box_number": 1313, "cm_result": {"image_url": "https://secim-images.oyveotesi.org/oyveotesi/blurred-min/server/13138_bulk_999999999_1684093293287519345.jpg", "submission_id": 468106, "total_vote": 340, "votes": {"1": 111, "2": 1, "3": 204, "4": 24}}, "mv_result": null, "school_name": "FAT\u0130H ANADOLU L\u0130SES\u0130"}, {"ballot_box_number": 1319, "cm_result": {"image_url": "https://secim-images.oyveotesi.org/oyveotesi/blurred-min/server/13138_bulk_999999999_1684093097106683327.jpg", "submission_id": 465304, "total_vote": 357, "votes": {"1": 129, "2": 2, "3": 205, "4": 21}}, "mv_result": {"image_url": "https://secim-images.oyveotesi.org/oyveotesi/blurred-min/server/13138_bulk_999999999_1684093097699847313.jpg", "submission_id": 465316, "total_vote": 344, "votes": {"1": 2, "10": 5, "11": 34, "12": 9, "21": 143, "22": 51, "24": 5, "6": 1, "7": 3, "8": 1, "9": 90}}, "school_name": "FAT\u0130H ANADOLU L\u0130SES\u0130"}, {"ballot_box_number": 1311, "cm_result": null, "mv_result": null, "school_name": "FAT\u0130H ANADOLU L\u0130SES\u0130"}, {"ballot_box_number": 1320, "cm_result": {"image_url": "https://secim-images.oyveotesi.org/oyveotesi/blurred-min/server/13138_bulk_999999999_1684093359013111857.jpg", "submission_id": 468902, "total_vote": 346, "votes": {"1": 117, "2": 1, "3": 201, "4": 27}}, "mv_result": {"image_url": "https://secim-images.oyveotesi.org/oyveotesi/blurred-min/server/13138_bulk_999999999_1684093410070883912.jpg", "submission_id": 469523, "total_vote": 347, "votes": {"1": 1, "10": 3, "11": 25, "12": 10, "16": 1, "21": 131, "22": 58, "23": 4, "24": 20, "4": 1, "6": 7, "7": 6, "8": 4, "9": 76}}, "school_name": "FAT\u0130H ANADOLU L\u0130SES\u0130"}, {"ballot_box_number": 1314, "cm_result": {"image_url": "https://secim-images.oyveotesi.org/oyveotesi/blurred-min/server/13138_bulk_999999999_1684093293093104386.jpg", "submission_id": 468098, "total_vote": 341, "votes": {"1": 115, "2": 1, "3": 197, "4": 28}}, "mv_result": null, "school_name": "FAT\u0130H ANADOLU L\u0130SES\u0130"}, {"ballot_box_number": 1321, "cm_result": {"image_url": "https://source3-secim-images.oyveotesi.org/blurred-min/bulk_download/v2/3b4b8099-d03c-41e7-ad66-72c13915fb99-1684106267026053522.jpg", "submission_id": 764206, "total_vote": 347, "votes": {"1": 127, "2": 0, "3": 201, "4": 19}}, "mv_result": {"image_url": "https://secim-images.oyveotesi.org/oyveotesi/blurred-min/server/13138_bulk_999999999_1684093097407508037.jpg", "submission_id": 465310, "total_vote": 340, "votes": {"1": 0, "10": 3, "11": 39, "12": 4, "16": 0, "17": 0, "18": 0, "19": 0, "2": 0, "21": 134, "22": 59, "23": 0, "24": 6, "3": 1, "4": 0, "5": 0, "6": 1, "7": 1, "8": 1, "9": 91}}, "school_name": "FAT\u0130H ANADOLU L\u0130SES\u0130"}, {"ballot_box_number": 1312, "cm_result": {"image_url": "https://secim-images.oyveotesi.org/oyveotesi/blurred-min/server/13138_bulk_999999999_1684093293126780541.jpg", "submission_id": 468101, "total_vote": 345, "votes": {"1": 119, "2": 1, "3": 213, "4": 12}}, "mv_result": {"image_url": "https://secim-images.oyveotesi.org/oyveotesi/blurred-min/server/13138_bulk_999999999_1684093097480614208.jpg", "submission_id": 465311, "total_vote": 341, "votes": {"10": 4, "11": 42, "12": 3, "17": 0, "18": 0, "19": 0, "2": 0, "21": 155, "22": 52, "23": 2, "24": 9, "3": 0, "4": 1, "5": 0, "6": 0, "7": 3, "8": 1, "9": 69}}, "school_name": "FAT\u0130H ANADOLU L\u0130SES\u0130"}]