[{"id": 6040, "name": "ADALA MAH."}, {"id": 6022, "name": "AK\u00d6REN MAH."}, {"id": 6066, "name": "AKSOY MAH."}, {"id": 6082, "name": "AKYAR MAH."}, {"id": 5992, "name": "ALLAHD\u0130YEN MAH."}, {"id": 6041, "name": "ATAT\u00dcRK MAH."}, {"id": 6005, "name": "BA\u011eCILAR MAH."}, {"id": 6049, "name": "BAH\u00c7EC\u0130K MAH."}, {"id": 6042, "name": "BARI\u015e MAH."}, {"id": 6083, "name": "BA\u015eLIO\u011eLU MAH."}, {"id": 6074, "name": "BE\u015eEYL\u00dcL MAH."}, {"id": 6090, "name": "BEYL\u0130KL\u0130 MAH."}, {"id": 6029, "name": "BURHAN MAH."}, {"id": 6067, "name": "CAFERBEY MAH."}, {"id": 6047, "name": "\u00c7AKALDO\u011eANLAR MAH."}, {"id": 6093, "name": "\u00c7ALTILI MAH."}, {"id": 6089, "name": "\u00c7AMURHAMAMI MAH."}, {"id": 6063, "name": "\u00c7APAKLI MAH."}, {"id": 6025, "name": "\u00c7AVLU MAH."}, {"id": 6064, "name": "\u00c7AYK\u00d6Y MAH."}, {"id": 6026, "name": "\u00c7AYPINAR MAH."}, {"id": 6021, "name": "\u00c7EL\u0130KL\u0130 MAH."}, {"id": 5996, "name": "\u00c7\u00d6KELEK MAH."}, {"id": 5995, "name": "\u00c7UKUROBA MAH."}, {"id": 6068, "name": "CUMHUR\u0130YET MAH."}, {"id": 6050, "name": "DAMATLI MAH."}, {"id": 6051, "name": "DEDETA\u015eI MAH."}, {"id": 6043, "name": "DEL\u0130BA\u015eLI MAH."}, {"id": 6084, "name": "DERBENT MAH."}, {"id": 6006, "name": "DOMBAYLI MAH."}, {"id": 6059, "name": "DURASILLI MAH."}, {"id": 6075, "name": "ELDELEK MAH."}, {"id": 6030, "name": "EM\u0130NBEY MAH."}, {"id": 5997, "name": "EM\u0130RHACILI MAH."}, {"id": 6052, "name": "ESK\u0130 CAM\u0130 MAH."}, {"id": 6076, "name": "GAFFAR OKKAN MAH."}, {"id": 6007, "name": "GAZ\u0130LER MAH."}, {"id": 6031, "name": "G\u00d6K\u00c7EK\u00d6Y MAH."}, {"id": 6077, "name": "G\u00d6KEY\u00dcP MAH."}, {"id": 6055, "name": "G\u00d6KK\u00d6Y MAH."}, {"id": 6032, "name": "G\u00dcM\u00dc\u015e MAH."}, {"id": 6078, "name": "G\u00dcNE\u015e MAH."}, {"id": 6079, "name": "HACIBEKTA\u015eLI MAH."}, {"id": 5998, "name": "HACIHIDIR MAH."}, {"id": 6011, "name": "HACIK\u00d6SEL\u0130 MAH."}, {"id": 6016, "name": "HACILI MAH."}, {"id": 6023, "name": "HASALAN MAH."}, {"id": 6014, "name": "\u0130\u011eDEC\u0130K MAH."}, {"id": 6069, "name": "KABAZLI MAH."}, {"id": 6060, "name": "KALE MAH."}, {"id": 6053, "name": "KAPANCI MAH."}, {"id": 6091, "name": "KAPLAN MAH."}, {"id": 6035, "name": "KARAA\u011eA\u00c7 MAH."}, {"id": 6085, "name": "KARAO\u011eLANLI MAH."}, {"id": 6056, "name": "KARAPINAR MAH."}, {"id": 6012, "name": "KARASAVCI MAH."}, {"id": 6033, "name": "KARAYAH\u015e\u0130 MAH."}, {"id": 6057, "name": "KEL\u0130 MAH."}, {"id": 6044, "name": "KEMERDAMLARI MAH."}, {"id": 6072, "name": "KEMER MAH."}, {"id": 6008, "name": "KIRDAMLARI MAH."}, {"id": 6054, "name": "KIRVEL\u0130 MAH."}, {"id": 6070, "name": "KIZILHAVLU MAH."}, {"id": 6036, "name": "KOCA\u00c7E\u015eME MAH."}, {"id": 5999, "name": "KORDON MAH."}, {"id": 5994, "name": "K\u00d6SEAL\u0130 MAH."}, {"id": 6037, "name": "KURTTUTAN MAH."}, {"id": 5993, "name": "KURTULU\u015e MAH."}, {"id": 6086, "name": "MAMATLI MAH."}, {"id": 6045, "name": "MERS\u0130NDERE MAH."}, {"id": 6092, "name": "MERS\u0130NL\u0130 MAH."}, {"id": 6038, "name": "MEVLUTLU MAH."}, {"id": 6000, "name": "M\u0130TATPA\u015eA MAH."}, {"id": 6087, "name": "NAMIK KEMAL MAH."}, {"id": 6017, "name": "ORAKLAR MAH."}, {"id": 6018, "name": "ORTAK\u00d6Y MAH."}, {"id": 6065, "name": "\u00d6ZYURT MAH."}, {"id": 6024, "name": "PAZARK\u00d6Y MAH."}, {"id": 6071, "name": "POYRAZDAMLARI MAH."}, {"id": 6034, "name": "POYRAZ MAH."}, {"id": 6039, "name": "SA\u011eLIK MAH."}, {"id": 6080, "name": "SARIPINAR MAH."}, {"id": 6061, "name": "SART MAH."}, {"id": 6004, "name": "\u015eEH\u0130TLER MAH."}, {"id": 6019, "name": "SEYRANTEPE MAH."}, {"id": 6020, "name": "S\u0130NDEL MAH."}, {"id": 6015, "name": "\u015e\u0130R\u0130NYER MAH."}, {"id": 6009, "name": "S\u00dcLEYMAN\u0130YE MAH."}, {"id": 6010, "name": "TAYTAN MAH."}, {"id": 6048, "name": "TEKEL\u0130O\u011eLU MAH."}, {"id": 6073, "name": "TORUNLU MAH."}, {"id": 6003, "name": "\u00dc\u00c7TEPE MAH."}, {"id": 6001, "name": "YA\u011eBASAN MAH."}, {"id": 6027, "name": "YA\u011eMURLAR MAH."}, {"id": 6028, "name": "YEN\u0130K\u00d6Y MAH."}, {"id": 6058, "name": "YEN\u0130PAZAR MAH."}, {"id": 6062, "name": "YE\u015e\u0130LKAVAK MAH."}, {"id": 6081, "name": "YE\u015e\u0130LOVA MAH."}, {"id": 6002, "name": "YE\u015e\u0130LYURT MAH."}, {"id": 6046, "name": "YILMAZ MAH."}, {"id": 6013, "name": "Y\u00d6R\u00dcK MAH."}, {"id": 6088, "name": "ZAFER MAH."}]