[{"ballot_box_number": 3133, "cm_result": {"image_url": "https://source3-secim-images.oyveotesi.org/blurred-min/bulk_download/v2/a0df7c7e-954f-4fd9-94d4-7a273a8a97ba-1684105104177473727.jpg", "submission_id": 571730, "total_vote": 242, "votes": {"1": 226, "2": 1, "3": 11, "4": 4}}, "mv_result": {"image_url": "https://source3-secim-images.oyveotesi.org/blurred-min/bulk_download/v2/cc6a2b19-7ee9-4a9e-a153-4524e2636cb6-1684105105855173720.jpg", "submission_id": 572004, "total_vote": 243, "votes": {"10": 15, "11": 38, "17": 1, "21": 7, "22": 7, "24": 1, "7": 1, "8": 3, "9": 170}}, "school_name": "G\u00dcVEN\u00c7 MAH. \u0130LKOKULU"}]