[{"ballot_box_number": 1232, "cm_result": {"image_url": "https://secim-images.oyveotesi.org/oyveotesi/blurred-min/server/361_bulk_999999999_1684082985706302863.jpg", "submission_id": 208468, "total_vote": 331, "votes": {"1": 109, "3": 212, "4": 10}}, "mv_result": {"image_url": "https://secim-images.oyveotesi.org/oyveotesi/blurred-min/server/361_bulk_999999999_1684084460428343319.jpg", "submission_id": 239487, "total_vote": 325, "votes": {"1": 0, "10": 0, "11": 41, "12": 1, "13": 8, "14": 0, "16": 0, "17": 0, "19": 0, "2": 0, "21": 132, "22": 62, "23": 2, "24": 1, "3": 0, "4": 0, "5": 0, "6": 1, "7": 2, "8": 6, "9": 69}}, "school_name": "M\u0130SAK\u00c7A D\u00dc\u011e\u00dcN SALONU"}]