[{"id": 32730, "name": "ATAK\u00d6Y MAH."}, {"id": 32731, "name": "AVLUOBASI MAH."}, {"id": 32723, "name": "AYDINEVLER MAH."}, {"id": 32737, "name": "AYDINLAR MAH."}, {"id": 32724, "name": "BAYRAM\u015eAH MAH."}, {"id": 32725, "name": "B\u00dcY\u00dcKKARAKARLI MAH."}, {"id": 32715, "name": "BUZA\u011eCI MAH."}, {"id": 32726, "name": "CAMBAZDERE MAH."}, {"id": 32716, "name": "CANHIDIR MAH."}, {"id": 32707, "name": "\u00c7ENE MAH."}, {"id": 32702, "name": "\u00c7ERKEZM\u00dcSELL\u0130M MAH."}, {"id": 32697, "name": "\u00c7IKRIK\u00c7I MAH."}, {"id": 32717, "name": "DAMBASLAR MAH."}, {"id": 32693, "name": "DAN\u0130\u015eMENT MAH."}, {"id": 32738, "name": "DEL\u0130BED\u0130R MAH."}, {"id": 32698, "name": "DU\u011eCALI MAH."}, {"id": 32708, "name": "EM\u0130RYAKUP MAH."}, {"id": 32732, "name": "FAHR\u0130O\u011eLU MAH."}, {"id": 32699, "name": "HACILLI MAH."}, {"id": 32710, "name": "HASK\u00d6Y MAH."}, {"id": 32727, "name": "HEDEYL\u0130 MAH."}, {"id": 32694, "name": "H\u0130SAR MAH."}, {"id": 32703, "name": "\u0130LYAS MAH."}, {"id": 32736, "name": "\u0130SMA\u0130LL\u0130 MAH."}, {"id": 32687, "name": "KABAH\u00d6Y\u00dcK MAH."}, {"id": 32711, "name": "KADR\u0130YE MAH."}, {"id": 32704, "name": "KAHYA MAH."}, {"id": 32728, "name": "KANDAMI\u015e MAH."}, {"id": 32733, "name": "KARABABA MAH."}, {"id": 32705, "name": "KARAB\u00dcR\u00c7EK MAH."}, {"id": 32734, "name": "KARAKAVAK MAH."}, {"id": 32712, "name": "KARAYAH\u015e\u0130 MAH."}, {"id": 32709, "name": "KEMALLAR MAH."}, {"id": 32718, "name": "KILI\u00c7LAR MAH."}, {"id": 32706, "name": "K\u00dc\u00c7\u00dcKKARAKARLI MAH."}, {"id": 32700, "name": "KURTDERE MAH."}, {"id": 32713, "name": "KUTLUG\u00dcN MAH."}, {"id": 32695, "name": "LAHNA MAH."}, {"id": 32719, "name": "MUZRUPLU MAH."}, {"id": 32692, "name": "\u00d6REY MAH."}, {"id": 32721, "name": "\u00d6VENLER MAH."}, {"id": 32735, "name": "PARMAKSIZ MAH."}, {"id": 32722, "name": "\u015eALGAMLI MAH."}, {"id": 32688, "name": "SOYLU MAH."}, {"id": 32720, "name": "SUBA\u015eI MAH."}, {"id": 32701, "name": "SUSUZM\u00dcSELL\u0130M MAH."}, {"id": 32689, "name": "TATARLI MAH."}, {"id": 32690, "name": "TEMREZL\u0130 MAH."}, {"id": 32691, "name": "UMURBEY MAH."}, {"id": 32729, "name": "UMUR\u00c7U MAH."}, {"id": 32714, "name": "Y\u00d6RG\u00dc\u00c7 MAH."}, {"id": 32696, "name": "Y\u00d6R\u00dcKLER MAH."}]